monnaie_converter/__init__.py
monnaie_converter/apps.py
monnaie_converter/forms.py
monnaie_converter/urls.py
monnaie_converter/views.py
monnaie_converter/static/monnaie_converter/style.css
monnaie_converter/templates/monnaie_converter/converter.html
monnaie_converter-0.1.2.dist-info/licenses/LICENSE
monnaie_converter-0.1.2.dist-info/METADATA
monnaie_converter-0.1.2.dist-info/WHEEL
monnaie_converter-0.1.2.dist-info/top_level.txt
monnaie_converter-0.1.2.dist-info/RECORD
