Metadata-Version: 2.4
Name: monnaie-converter
Version: 0.1.2
Summary: Un package Django pour convertir les monnaies avec un formulaire simple
Author-email: Nicosidick <abou210traore@email.com>
License: MIT
Project-URL: Homepage, https://pypi.org/project/monnaie-converter/
Requires-Python: >=3.7
License-File: LICENSE
Requires-Dist: Django>=3.2
Dynamic: license-file
